adafruit_usb_host_midi.py
adafruit_circuitpython_usb_host_midi-0.8.5.dist-info/licenses/LICENSE
adafruit_circuitpython_usb_host_midi-0.8.5.dist-info/METADATA
adafruit_circuitpython_usb_host_midi-0.8.5.dist-info/WHEEL
adafruit_circuitpython_usb_host_midi-0.8.5.dist-info/top_level.txt
adafruit_circuitpython_usb_host_midi-0.8.5.dist-info/RECORD
