Metadata-Version: 2.4
Name: adafruit-circuitpython-usb-host-midi
Version: 0.8.5
Summary: CircuitPython USB host driver for MIDI devices
Author-email: Adafruit Industries <circuitpython@adafruit.com>
License: MIT
Project-URL: Homepage, https://github.com/adafruit/Adafruit_CircuitPython_USB_Host_MIDI
Keywords: adafruit,blinka,circuitpython,micropython,usb-host-midi,midi
Classifier: Intended Audience :: Developers
Classifier: Topic :: Software Development :: Libraries
Classifier: Topic :: Software Development :: Embedded Systems
Classifier: Topic :: System :: Hardware
Classifier: License :: OSI Approved :: MIT License
Classifier: Programming Language :: Python :: 3
License-File: LICENSE
Requires-Dist: Adafruit-Blinka
Requires-Dist: adafruit-circuitpython-usb-host-descriptors
Requires-Dist: pyusb
Provides-Extra: optional
Dynamic: license-file
